receipt_enhancer/__init__.py
receipt_enhancer/receipt_enhancer.py
receipt_enhancer-0.1.8.dist-info/LICENSE
receipt_enhancer-0.1.8.dist-info/METADATA
receipt_enhancer-0.1.8.dist-info/WHEEL
receipt_enhancer-0.1.8.dist-info/RECORD
