Metadata-Version: 2.1
Name: receipt-enhancer
Version: 0.1.8
Summary: This module is essential for preprocessing receipt images to improve visual quality and facilitate automatic analysis.
License: MIT
Keywords: document,nfe,invoice,receipt
Author: Ricardo Castro
Author-email: srrenks@gmail.com
Requires-Python: >=3.8,<4.0
Classifier: License :: OSI Approved :: MIT License
Classifier: Programming Language :: Python :: 3
Classifier: Programming Language :: Python :: 3.8
Classifier: Programming Language :: Python :: 3.9
Classifier: Programming Language :: Python :: 3.10
Classifier: Programming Language :: Python :: 3.11
Classifier: Programming Language :: Python :: 3.12
Requires-Dist: numpy (>=1.26.4,<2.0.0)
Requires-Dist: opencv-python (>=4.9.0.80,<5.0.0.0)
